{
  "id": "ecommerce-checkout-flow",
  "name": "Checkout Flow",
  "category": "ecommerce",
  "description": "Complete checkout experience with cart review, shipping, and payment",
  "files": [
    { "path": "lib/checkout/checkout-context.tsx", "template": "lib/checkout-context.tsx" },
    { "path": "lib/checkout/checkout-utils.ts", "template": "lib/checkout-utils.ts" },
    { "path": "app/checkout/page.tsx", "template": "app/checkout/page.tsx" },
    { "path": "app/checkout/success/page.tsx", "template": "app/success/page.tsx" },
    { "path": "app/checkout/cancel/page.tsx", "template": "app/cancel/page.tsx" },
    { "path": "components/checkout/CheckoutForm.tsx", "template": "components/CheckoutForm.tsx" },
    { "path": "components/checkout/CheckoutSummary.tsx", "template": "components/CheckoutSummary.tsx" },
    { "path": "components/checkout/ShippingForm.tsx", "template": "components/ShippingForm.tsx" },
    { "path": "components/checkout/PaymentForm.tsx", "template": "components/PaymentForm.tsx" },
    { "path": "hooks/useCheckout.ts", "template": "hooks/useCheckout.ts" }
  ],
  "dependencies": {
    "npm": {
      "zod": "^3.22.4"
    },
    "features": ["ecommerce-shopping-cart"],
    "integrations": ["payments"]
  },
  "previewComponent": "PricingPlans"
}

